moeysaklaksd/__init__.py
moeysaklaksd/worldtime.py
moeysaklaksd-0.1.dist-info/METADATA
moeysaklaksd-0.1.dist-info/WHEEL
moeysaklaksd-0.1.dist-info/top_level.txt
moeysaklaksd-0.1.dist-info/RECORD
