Metadata-Version: 2.1
Name: moeysaklaksd
Version: 0.1
Summary: fethcer
Author: Lexy
Requires-Dist: requests
